<w:p w:rsidR="003C2CC5" w:rsidRDefault="003C2CC5" w:rsidP="00FE63F7">
  <w:pPr>
    <w:pStyle w:val="berschrift2"/>
    <w:spacing w:before="240" w:after="60"/>
    <w:ind w:left="0" w:right="0"/>
  </w:pPr>
  <w:bookmarkStart w:id="21" w:name="_Hlk519600367"/>
  <w:r>
    <w:rPr>
      <w:vanish />
    </w:rPr>
    <!-- set requirement id -->
    <w:t>{ "requirement-id": "{{ requirement.id }}", "requirement-state": "start" }</w:t>
    <!-- set requirement id -->
  </w:r>
  <w:r>
    <w:rPr>
      <w:rFonts w:ascii="Arial" w:eastAsia="Arial" w:hAnsi="Arial" w:cs="Arial"/>
      <w:sz w:val="27"/>
    </w:rPr>
    <!-- title number -->
    <w:t>3.{{ counter }}</w:t>
    <!-- title number -->
  </w:r>
  <w:r>
    <w:t xml:space="preserve">       </w:t>
  </w:r>
  <w:bookmarkStart w:id="22" w:name="_Toc164172951"/>
  <w:bookmarkEnd w:id="22"/>
  <w:r>
    <w:rPr>
      <w:rFonts w:ascii="Arial" w:eastAsia="Arial" w:hAnsi="Arial" w:cs="Arial"/>
      <w:sz w:val="27"/>
    </w:rPr>
    <!-- title -->
    <w:t>Anforderung {{ counter }}</w:t>
    <!-- title -->
  </w:r>
  <w:r>
    <w:t xml:space="preserve"> </w:t>
  </w:r>
</w:p>
<w:tbl>
  <w:tblPr>
    <w:tblStyle w:val="Gitternetztabelle1hell"/>
    <w:tblW w:w="9495" w:type="dxa"/>
    <w:tblInd w:w="0" w:type="dxa"/>
    <w:tblLayout w:type="fixed"/>
    <w:tblLook w:val="04A0" w:firstRow="1" w:lastRow="0" w:firstColumn="1" w:lastColumn="0" w:noHBand="0" w:noVBand="1"/>
  </w:tblPr>
  <w:tblGrid>
    <w:gridCol w:w="2548"/>
    <w:gridCol w:w="2126"/>
    <w:gridCol w:w="1843"/>
    <w:gridCol w:w="2978"/>
  </w:tblGrid>
  <w:tr w:rsidR="003C2CC5" w:rsidTr="00FE63F7">
    <w:trPr>
      <w:cnfStyle w:val="100000000000" w:firstRow="1" w:lastRow="0" w:firstColumn="0" w:lastColumn="0" w:oddVBand="0" w:evenVBand="0" w:oddHBand="0" w:evenHBand="0" w:firstRowFirstColumn="0" w:firstRowLastColumn="0" w:lastRowFirstColumn="0" w:lastRowLastColumn="0"/>
      <w:trHeight w:val="317"/>
    </w:trPr>
    <w:tc>
      <w:tcPr>
        <w:cnfStyle w:val="001000000000" w:firstRow="0" w:lastRow="0" w:firstColumn="1" w:lastColumn="0" w:oddVBand="0" w:evenVBand="0" w:oddHBand="0" w:evenHBand="0" w:firstRowFirstColumn="0" w:firstRowLastColumn="0" w:lastRowFirstColumn="0" w:lastRowLastColumn="0"/>
        <w:tcW w:w="2547" w:type="dxa"/>
        <w:tcBorders>
          <w:top w:val="single" w:sz="4" w:space="0" w:color="999999" w:themeColor="text1" w:themeTint="66"/>
          <w:left w:val="single" w:sz="4" w:space="0" w:color="999999" w:themeColor="text1" w:themeTint="66"/>
          <w:bottom w:val="single" w:sz="4" w:space="0" w:color="999999" w:themeColor="text1" w:themeTint="66"/>
          <w:right w:val="single" w:sz="4" w:space="0" w:color="999999" w:themeColor="text1" w:themeTint="66"/>
        </w:tcBorders>
        <w:hideMark/>
      </w:tcPr>
      <w:p w:rsidR="003C2CC5" w:rsidRDefault="003C2CC5">
        <w:pPr>
          <w:spacing w:before="40"/>
          <w:rPr>
            <w:rFonts w:ascii="Arial" w:hAnsi="Arial" w:cs="Arial"/>
          </w:rPr>
        </w:pPr>
        <w:r>
          <w:rPr>
            <w:rFonts w:ascii="Arial" w:eastAsia="Tahoma" w:hAnsi="Arial" w:cs="Arial"/>
            <w:sz w:val="20"/>
          </w:rPr>
          <w:t>Nr. / ID</w:t>
        </w:r>
        <w:r>
          <w:rPr>
            <w:rFonts w:ascii="Arial" w:hAnsi="Arial" w:cs="Arial"/>
          </w:rPr>
          <w:t xml:space="preserve"> </w:t>
        </w:r>
      </w:p>
    </w:tc>
    <w:tc>
      <w:tcPr>
        <w:tcW w:w="2126" w:type="dxa"/>
        <w:tcBorders>
          <w:top w:val="single" w:sz="4" w:space="0" w:color="999999" w:themeColor="text1" w:themeTint="66"/>
          <w:left w:val="single" w:sz="4" w:space="0" w:color="999999" w:themeColor="text1" w:themeTint="66"/>
          <w:bottom w:val="single" w:sz="4" w:space="0" w:color="999999" w:themeColor="text1" w:themeTint="66"/>
          <w:right w:val="single" w:sz="4" w:space="0" w:color="999999" w:themeColor="text1" w:themeTint="66"/>
        </w:tcBorders>
        <w:hideMark/>
      </w:tcPr>
      <w:p w:rsidR="003C2CC5" w:rsidRDefault="003C2CC5">
        <w:pPr>
          <w:spacing w:after="220"/>
          <w:cnfStyle w:val="100000000000" w:firstRow="1" w:lastRow="0" w:firstColumn="0" w:lastColumn="0" w:oddVBand="0" w:evenVBand="0" w:oddHBand="0" w:evenHBand="0" w:firstRowFirstColumn="0" w:firstRowLastColumn="0" w:lastRowFirstColumn="0" w:lastRowLastColumn="0"/>
          <w:rPr>
            <w:rFonts w:ascii="Arial" w:eastAsia="Tahoma" w:hAnsi="Arial" w:cs="Arial"/>
            <w:sz w:val="20"/>
          </w:rPr>
        </w:pPr>
        <w:sdt>
          <w:sdtPr>
            <w:rPr>
              <w:rFonts w:ascii="Arial" w:eastAsia="Tahoma" w:hAnsi="Arial" w:cs="Arial"/>
              <w:sz w:val="20"/>
            </w:rPr>
            <w:alias w:val="requirement_{{ requirement.id }}_id"/>
            <w:tag w:val="requirement_{{ requirement.id }}_id"/>
            <w:id w:val="-1394802603"/>
            <w:placeholder>
              <w:docPart w:val="1F124D4053BE47D89262535525CB9897"/>
            </w:placeholder>
          </w:sdtPr>
          <w:sdtContent>
            <w:r>
              <w:rPr>
                <w:rFonts w:ascii="Arial" w:eastAsia="Tahoma" w:hAnsi="Arial" w:cs="Arial"/>
                <w:sz w:val="20"/>
                <w:lang w:val="de-DE"/>
              </w:rPr>
              <w:t>{{ requirement.id }}</w:t>
            </w:r>
            <w:r>
              <w:rPr>
                <w:rFonts w:ascii="Arial" w:eastAsia="Tahoma" w:hAnsi="Arial" w:cs="Arial"/>
                <w:sz w:val="20"/>
              </w:rPr>
              <w:t>  </w:t>
            </w:r>
          </w:sdtContent>
        </w:sdt>
        <w:r>
          <w:rPr>
            <w:rFonts w:ascii="Arial" w:eastAsia="Tahoma" w:hAnsi="Arial" w:cs="Arial"/>
            <w:sz w:val="20"/>
          </w:rPr>
          <w:t xml:space="preserve">         </w:t>
        </w:r>
      </w:p>
    </w:tc>
    <w:tc>
      <w:tcPr>
        <w:tcW w:w="1843" w:type="dxa"/>
        <w:tcBorders>
          <w:top w:val="single" w:sz="4" w:space="0" w:color="999999" w:themeColor="text1" w:themeTint="66"/>
          <w:left w:val="single" w:sz="4" w:space="0" w:color="999999" w:themeColor="text1" w:themeTint="66"/>
          <w:bottom w:val="single" w:sz="4" w:space="0" w:color="999999" w:themeColor="text1" w:themeTint="66"/>
          <w:right w:val="single" w:sz="4" w:space="0" w:color="999999" w:themeColor="text1" w:themeTint="66"/>
        </w:tcBorders>
        <w:hideMark/>
      </w:tcPr>
      <w:p w:rsidR="003C2CC5" w:rsidRDefault="003C2CC5">
        <w:pPr>
          <w:spacing w:before="40"/>
          <w:cnfStyle w:val="100000000000" w:firstRow="1" w:lastRow="0" w:firstColumn="0" w:lastColumn="0" w:oddVBand="0" w:evenVBand="0" w:oddHBand="0" w:evenHBand="0" w:firstRowFirstColumn="0" w:firstRowLastColumn="0" w:lastRowFirstColumn="0" w:lastRowLastColumn="0"/>
          <w:rPr>
            <w:rFonts w:ascii="Arial" w:hAnsi="Arial" w:cs="Arial"/>
          </w:rPr>
        </w:pPr>
        <w:r>
          <w:rPr>
            <w:rFonts w:ascii="Arial" w:eastAsia="Tahoma" w:hAnsi="Arial" w:cs="Arial"/>
            <w:sz w:val="20"/>
            <w:lang w:val="de-DE"/>
          </w:rPr>
          <w:t>Version</w:t>
        </w:r>
        <w:r>
          <w:rPr>
            <w:rFonts w:ascii="Arial" w:hAnsi="Arial" w:cs="Arial"/>
          </w:rPr>
          <w:t xml:space="preserve"> </w:t>
        </w:r>
      </w:p>
    </w:tc>
    <w:tc>
      <w:tcPr>
        <w:tcW w:w="2977" w:type="dxa"/>
        <w:tcBorders>
          <w:top w:val="single" w:sz="4" w:space="0" w:color="999999" w:themeColor="text1" w:themeTint="66"/>
          <w:left w:val="single" w:sz="4" w:space="0" w:color="999999" w:themeColor="text1" w:themeTint="66"/>
          <w:bottom w:val="single" w:sz="4" w:space="0" w:color="999999" w:themeColor="text1" w:themeTint="66"/>
          <w:right w:val="single" w:sz="4" w:space="0" w:color="999999" w:themeColor="text1" w:themeTint="66"/>
        </w:tcBorders>
        <w:hideMark/>
      </w:tcPr>
      <w:p w:rsidR="003C2CC5" w:rsidRDefault="003C2CC5">
        <w:pPr>
          <w:spacing w:before="40"/>
          <w:cnfStyle w:val="100000000000" w:firstRow="1" w:lastRow="0" w:firstColumn="0" w:lastColumn="0" w:oddVBand="0" w:evenVBand="0" w:oddHBand="0" w:evenHBand="0" w:firstRowFirstColumn="0" w:firstRowLastColumn="0" w:lastRowFirstColumn="0" w:lastRowLastColumn="0"/>
          <w:rPr>
            <w:rFonts w:ascii="Arial" w:hAnsi="Arial" w:cs="Arial"/>
          </w:rPr>
        </w:pPr>
        <w:sdt>
          <w:sdtPr>
            <w:rPr>
              <w:rFonts w:ascii="Arial" w:eastAsia="Tahoma" w:hAnsi="Arial" w:cs="Arial"/>
              <w:sz w:val="20"/>
            </w:rPr>
            <w:alias w:val="requirement_{{ requirement.id }}_version"/>
            <w:tag w:val="requirement_{{ requirement.id }}_version"/>
            <w:id w:val="1561210156"/>
            <w:placeholder>
              <w:docPart w:val="E6EEA645379D4434BCE4175FCD863B76"/>
            </w:placeholder>
          </w:sdtPr>
          <w:sdtContent>
            <w:r>
              <w:rPr>
                <w:rFonts w:ascii="Arial" w:eastAsia="Tahoma" w:hAnsi="Arial" w:cs="Arial"/>
                <w:sz w:val="20"/>
                <w:lang w:val="de-DE"/>
              </w:rPr>
              <w:t>{{ requirement.version }}</w:t>
            </w:r>
            <w:r>
              <w:rPr>
                <w:rFonts w:ascii="Arial" w:eastAsia="Tahoma" w:hAnsi="Arial" w:cs="Arial"/>
                <w:sz w:val="20"/>
              </w:rPr>
              <w:t>  </w:t>
            </w:r>
          </w:sdtContent>
        </w:sdt>
        <w:r>
          <w:rPr>
            <w:rFonts w:ascii="Arial" w:eastAsia="Tahoma" w:hAnsi="Arial" w:cs="Arial"/>
            <w:sz w:val="20"/>
          </w:rPr>
          <w:t>        </w:t>
        </w:r>
      </w:p>
    </w:tc>
  </w:tr>
  <w:tr w:rsidR="003C2CC5" w:rsidTr="00FE63F7">
    <w:tc>
      <w:tcPr>
        <w:cnfStyle w:val="001000000000" w:firstRow="0" w:lastRow="0" w:firstColumn="1" w:lastColumn="0" w:oddVBand="0" w:evenVBand="0" w:oddHBand="0" w:evenHBand="0" w:firstRowFirstColumn="0" w:firstRowLastColumn="0" w:lastRowFirstColumn="0" w:lastRowLastColumn="0"/>
        <w:tcW w:w="2547" w:type="dxa"/>
        <w:tcBorders>
          <w:top w:val="single" w:sz="4" w:space="0" w:color="999999" w:themeColor="text1" w:themeTint="66"/>
          <w:left w:val="single" w:sz="4" w:space="0" w:color="999999" w:themeColor="text1" w:themeTint="66"/>
          <w:bottom w:val="single" w:sz="4" w:space="0" w:color="999999" w:themeColor="text1" w:themeTint="66"/>
          <w:right w:val="single" w:sz="4" w:space="0" w:color="999999" w:themeColor="text1" w:themeTint="66"/>
        </w:tcBorders>
        <w:hideMark/>
      </w:tcPr>
      <w:p w:rsidR="003C2CC5" w:rsidRDefault="003C2CC5">
        <w:pPr>
          <w:spacing w:before="40"/>
          <w:rPr>
            <w:rFonts w:ascii="Arial" w:hAnsi="Arial" w:cs="Arial"/>
          </w:rPr>
        </w:pPr>
        <w:r>
          <w:rPr>
            <w:rFonts w:ascii="Arial" w:eastAsia="Tahoma" w:hAnsi="Arial" w:cs="Arial"/>
            <w:sz w:val="20"/>
          </w:rPr>
          <w:t xml:space="preserve">Nichttechnischer Tittel              </w:t>
        </w:r>
      </w:p>
    </w:tc>
    <w:tc>
      <w:tcPr>
        <w:tcW w:w="2126" w:type="dxa"/>
        <w:tcBorders>
          <w:top w:val="single" w:sz="4" w:space="0" w:color="999999" w:themeColor="text1" w:themeTint="66"/>
          <w:left w:val="single" w:sz="4" w:space="0" w:color="999999" w:themeColor="text1" w:themeTint="66"/>
          <w:bottom w:val="single" w:sz="4" w:space="0" w:color="999999" w:themeColor="text1" w:themeTint="66"/>
          <w:right w:val="single" w:sz="4" w:space="0" w:color="999999" w:themeColor="text1" w:themeTint="66"/>
        </w:tcBorders>
        <w:hideMark/>
      </w:tcPr>
      <w:p w:rsidR="003C2CC5" w:rsidRDefault="003C2CC5">
        <w:pPr>
          <w:spacing w:before="40"/>
          <w:cnfStyle w:val="000000000000" w:firstRow="0" w:lastRow="0" w:firstColumn="0" w:lastColumn="0" w:oddVBand="0" w:evenVBand="0" w:oddHBand="0" w:evenHBand="0" w:firstRowFirstColumn="0" w:firstRowLastColumn="0" w:lastRowFirstColumn="0" w:lastRowLastColumn="0"/>
          <w:rPr>
            <w:rFonts w:ascii="Arial" w:hAnsi="Arial" w:cs="Arial"/>
          </w:rPr>
        </w:pPr>
        <w:sdt>
          <w:sdtPr>
            <w:rPr>
              <w:rFonts w:ascii="Arial" w:eastAsia="Tahoma" w:hAnsi="Arial" w:cs="Arial"/>
              <w:sz w:val="20"/>
            </w:rPr>
            <w:alias w:val="requirement_{{ requirement.id }}_name"/>
            <w:tag w:val="requirement_{{ requirement.id }}_name"/>
            <w:id w:val="-1800447998"/>
            <w:placeholder>
              <w:docPart w:val="022BBB41EB32424B927075DA94871523"/>
            </w:placeholder>
          </w:sdtPr>
          <w:sdtContent>
            <w:r>
              <w:rPr>
                <w:rFonts w:ascii="Arial" w:eastAsia="Tahoma" w:hAnsi="Arial" w:cs="Arial"/>
                <w:sz w:val="20"/>
                <w:lang w:val="de-DE"/>
              </w:rPr>
              <w:t>{{ requirement.name }}</w:t>
            </w:r>
            <w:r>
              <w:rPr>
                <w:rFonts w:ascii="Arial" w:eastAsia="Tahoma" w:hAnsi="Arial" w:cs="Arial"/>
                <w:sz w:val="20"/>
              </w:rPr>
              <w:t>  </w:t>
            </w:r>
          </w:sdtContent>
        </w:sdt>
        <w:r>
          <w:rPr>
            <w:rFonts w:ascii="Arial" w:eastAsia="Tahoma" w:hAnsi="Arial" w:cs="Arial"/>
            <w:sz w:val="20"/>
          </w:rPr>
          <w:t>  </w:t>
        </w:r>
      </w:p>
    </w:tc>
    <w:tc>
      <w:tcPr>
        <w:tcW w:w="1843" w:type="dxa"/>
        <w:tcBorders>
          <w:top w:val="single" w:sz="4" w:space="0" w:color="999999" w:themeColor="text1" w:themeTint="66"/>
          <w:left w:val="single" w:sz="4" w:space="0" w:color="999999" w:themeColor="text1" w:themeTint="66"/>
          <w:bottom w:val="single" w:sz="4" w:space="0" w:color="999999" w:themeColor="text1" w:themeTint="66"/>
          <w:right w:val="single" w:sz="4" w:space="0" w:color="999999" w:themeColor="text1" w:themeTint="66"/>
        </w:tcBorders>
        <w:hideMark/>
      </w:tcPr>
      <w:p w:rsidR="003C2CC5" w:rsidRDefault="003C2CC5">
        <w:pPr>
          <w:spacing w:before="40"/>
          <w:cnfStyle w:val="000000000000" w:firstRow="0" w:lastRow="0" w:firstColumn="0" w:lastColumn="0" w:oddVBand="0" w:evenVBand="0" w:oddHBand="0" w:evenHBand="0" w:firstRowFirstColumn="0" w:firstRowLastColumn="0" w:lastRowFirstColumn="0" w:lastRowLastColumn="0"/>
          <w:rPr>
            <w:rFonts w:ascii="Arial" w:hAnsi="Arial" w:cs="Arial"/>
          </w:rPr>
        </w:pPr>
        <w:r>
          <w:rPr>
            <w:rFonts w:ascii="Arial" w:eastAsia="Tahoma" w:hAnsi="Arial" w:cs="Arial"/>
            <w:sz w:val="20"/>
            <w:lang w:val="de-DE"/>
          </w:rPr>
          <w:t>Aufwand</w:t>
        </w:r>
        <w:r>
          <w:rPr>
            <w:rFonts w:ascii="Arial" w:hAnsi="Arial" w:cs="Arial"/>
          </w:rPr>
          <w:t xml:space="preserve"> </w:t>
        </w:r>
      </w:p>
    </w:tc>
    <w:tc>
      <w:tcPr>
        <w:tcW w:w="2977" w:type="dxa"/>
        <w:tcBorders>
          <w:top w:val="single" w:sz="4" w:space="0" w:color="999999" w:themeColor="text1" w:themeTint="66"/>
          <w:left w:val="single" w:sz="4" w:space="0" w:color="999999" w:themeColor="text1" w:themeTint="66"/>
          <w:bottom w:val="single" w:sz="4" w:space="0" w:color="999999" w:themeColor="text1" w:themeTint="66"/>
          <w:right w:val="single" w:sz="4" w:space="0" w:color="999999" w:themeColor="text1" w:themeTint="66"/>
        </w:tcBorders>
        <w:hideMark/>
      </w:tcPr>
      <w:p w:rsidR="003C2CC5" w:rsidRDefault="003C2CC5">
        <w:pPr>
          <w:spacing w:before="40"/>
          <w:cnfStyle w:val="000000000000" w:firstRow="0" w:lastRow="0" w:firstColumn="0" w:lastColumn="0" w:oddVBand="0" w:evenVBand="0" w:oddHBand="0" w:evenHBand="0" w:firstRowFirstColumn="0" w:firstRowLastColumn="0" w:lastRowFirstColumn="0" w:lastRowLastColumn="0"/>
          <w:rPr>
            <w:rFonts w:ascii="Arial" w:hAnsi="Arial" w:cs="Arial"/>
          </w:rPr>
        </w:pPr>
        <w:r>
          <w:rPr>
            <w:rFonts w:ascii="Arial" w:eastAsia="Tahoma" w:hAnsi="Arial" w:cs="Arial"/>
            <w:sz w:val="20"/>
          </w:rPr>
          <w:t> </w:t>
        </w:r>
        <w:sdt>
          <w:sdtPr>
            <w:rPr>
              <w:rFonts w:ascii="Arial" w:eastAsia="Tahoma" w:hAnsi="Arial" w:cs="Arial"/>
              <w:sz w:val="20"/>
            </w:rPr>
            <w:alias w:val="requirement_{{ requirement.id }}_duration"/>
            <w:tag w:val="requirement_{{ requirement.id }}_duration"/>
            <w:id w:val="-1304768493"/>
            <w:placeholder>
              <w:docPart w:val="FC39EACEDB6E460995FDC45D60349DB2"/>
            </w:placeholder>
          </w:sdtPr>
          <w:sdtContent>
            <w:r>
              <w:rPr>
                <w:rFonts w:ascii="Arial" w:eastAsia="Tahoma" w:hAnsi="Arial" w:cs="Arial"/>
                <w:sz w:val="20"/>
                <w:lang w:val="de-DE"/>
              </w:rPr>
              <w:t>{{ requirement.duration }} h</w:t>
            </w:r>
            <w:r>
              <w:rPr>
                <w:rFonts w:ascii="Arial" w:eastAsia="Tahoma" w:hAnsi="Arial" w:cs="Arial"/>
                <w:sz w:val="20"/>
              </w:rPr>
              <w:t>  </w:t>
            </w:r>
          </w:sdtContent>
        </w:sdt>
        <w:r>
          <w:rPr>
            <w:rFonts w:ascii="Arial" w:eastAsia="Tahoma" w:hAnsi="Arial" w:cs="Arial"/>
            <w:sz w:val="20"/>
          </w:rPr>
          <w:t>        </w:t>
        </w:r>
      </w:p>
    </w:tc>
  </w:tr>
</w:tbl>
<w:p w:rsidR="003C2CC5" w:rsidRDefault="003C2CC5" w:rsidP="00FE63F7">
  <w:pPr>
    <w:pStyle w:val="berschrift3"/>
    <w:spacing w:before="240" w:after="60"/>
    <w:ind w:left="0" w:right="0"/>
  </w:pPr>
  <w:r>
    <w:rPr>
      <w:rFonts w:ascii="Arial" w:eastAsia="Arial" w:hAnsi="Arial" w:cs="Arial"/>
    </w:rPr>
    <!-- subtitle 1 number-->
    <w:t>3.{{ counter }}.1</w:t>
    <!-- subtitle 1 number-->
  </w:r>
  <w:r>
    <w:t xml:space="preserve"> </w:t>
  </w:r>
  <w:bookmarkStart w:id="23" w:name="_Toc164172952"/>
  <w:bookmarkEnd w:id="23"/>
  <w:r>
    <w:rPr>
      <w:rFonts w:ascii="Arial" w:eastAsia="Arial" w:hAnsi="Arial" w:cs="Arial"/>
    </w:rPr>
    <!-- subtitle 1 -->
    <w:t>Beschreibung</w:t>
    <!-- subtitle 1 -->
  </w:r>
  <w:r>
    <w:t xml:space="preserve"> </w:t>
  </w:r>
</w:p>
<w:p w:rsidR="003C2CC5" w:rsidRDefault="003C2CC5" w:rsidP="00FE63F7">
  <w:pPr>
    <w:spacing w:after="220"/>
    <w:rPr>
      <w:rFonts w:ascii="Tahoma" w:eastAsia="Tahoma" w:hAnsi="Tahoma" w:cs="Tahoma"/>
      <w:sz w:val="20"/>
    </w:rPr>
  </w:pPr>
  <w:sdt>
    <w:sdtPr>
      <w:rPr>
        <w:rFonts w:ascii="Tahoma" w:eastAsia="Tahoma" w:hAnsi="Tahoma" w:cs="Tahoma"/>
        <w:sz w:val="20"/>
      </w:rPr>
      <w:alias w:val="requirement_{{ requirement.id }}_description"/>
      <w:tag w:val="requirement_{{ requirement.id }}_description"/>
      <w:id w:val="-235323408"/>
      <w:placeholder>
        <w:docPart w:val="1D3F8E95024149CCA6A0A503AA94586C"/>
      </w:placeholder>
    </w:sdtPr>
    <w:sdtContent>
      <w:r>
        <w:rPr>
          <w:rFonts w:ascii="Tahoma" w:eastAsia="Tahoma" w:hAnsi="Tahoma" w:cs="Tahoma"/>
          <w:sz w:val="20"/>
          <w:lang w:val="de-DE"/>
        </w:rPr>
        <w:t>{{ requirement.description }}</w:t>
      </w:r>
      <w:r>
        <w:rPr>
          <w:rFonts w:ascii="Tahoma" w:eastAsia="Tahoma" w:hAnsi="Tahoma" w:cs="Tahoma"/>
          <w:sz w:val="20"/>
        </w:rPr>
        <w:t>  </w:t>
      </w:r>
    </w:sdtContent>
  </w:sdt>
  <w:r>
    <w:rPr>
      <w:rFonts w:ascii="Tahoma" w:eastAsia="Tahoma" w:hAnsi="Tahoma" w:cs="Tahoma"/>
      <w:sz w:val="20"/>
    </w:rPr>
    <w:t xml:space="preserve">         </w:t>
  </w:r>
</w:p>
<w:p w:rsidR="003C2CC5" w:rsidRDefault="003C2CC5" w:rsidP="00FE63F7">
  <w:pPr>
    <w:pStyle w:val="berschrift3"/>
    <w:spacing w:before="240" w:after="60"/>
    <w:ind w:left="0" w:right="0"/>
  </w:pPr>
  <w:r>
    <w:rPr>
      <w:rFonts w:ascii="Arial" w:eastAsia="Arial" w:hAnsi="Arial" w:cs="Arial"/>
    </w:rPr>
    <w:t>3.{{ counter }}.2</w:t>
  </w:r>
  <w:r>
    <w:t xml:space="preserve"> </w:t>
  </w:r>
  <w:bookmarkStart w:id="24" w:name="_Toc164172953"/>
  <w:bookmarkEnd w:id="24"/>
  <w:r>
    <w:rPr>
      <w:rFonts w:ascii="Arial" w:eastAsia="Arial" w:hAnsi="Arial" w:cs="Arial"/>
    </w:rPr>
    <w:t>Wechselwirkungen</w:t>
  </w:r>
  <w:r>
    <w:t xml:space="preserve"> </w:t>
  </w:r>
</w:p>
<w:p w:rsidR="003C2CC5" w:rsidRDefault="003C2CC5" w:rsidP="00FE63F7">
  <w:pPr>
    <w:spacing w:after="220"/>
  </w:pPr>
  <w:r>
    <w:rPr>
      <w:rFonts w:ascii="Tahoma" w:eastAsia="Tahoma" w:hAnsi="Tahoma" w:cs="Tahoma"/>
      <w:sz w:val="20"/>
    </w:rPr>
    <w:t>&lt;Ihr Text&gt;</w:t>
  </w:r>
  <w:r>
    <w:t xml:space="preserve"> </w:t>
  </w:r>
</w:p>
<w:p w:rsidR="003C2CC5" w:rsidRDefault="003C2CC5" w:rsidP="00FE63F7">
  <w:pPr>
    <w:pStyle w:val="berschrift3"/>
    <w:spacing w:before="240" w:after="60"/>
    <w:ind w:left="0" w:right="0"/>
  </w:pPr>
  <w:r>
    <w:rPr>
      <w:rFonts w:ascii="Arial" w:eastAsia="Arial" w:hAnsi="Arial" w:cs="Arial"/>
    </w:rPr>
    <w:t>3.{{ counter }}.3</w:t>
  </w:r>
  <w:r>
    <w:t xml:space="preserve"> </w:t>
  </w:r>
  <w:bookmarkStart w:id="25" w:name="_Toc164172954"/>
  <w:bookmarkEnd w:id="25"/>
  <w:r>
    <w:rPr>
      <w:rFonts w:ascii="Arial" w:eastAsia="Arial" w:hAnsi="Arial" w:cs="Arial"/>
    </w:rPr>
    <w:t>Risiken</w:t>
  </w:r>
  <w:r>
    <w:t xml:space="preserve"> </w:t>
  </w:r>
</w:p>
<w:p w:rsidR="003C2CC5" w:rsidRDefault="003C2CC5" w:rsidP="00FE63F7">
  <w:pPr>
    <w:spacing w:after="220"/>
  </w:pPr>
  <w:r>
    <w:rPr>
      <w:rFonts w:ascii="Tahoma" w:eastAsia="Tahoma" w:hAnsi="Tahoma" w:cs="Tahoma"/>
      <w:sz w:val="20"/>
    </w:rPr>
    <w:t>&lt;Ihr Text&gt;</w:t>
  </w:r>
  <w:r>
    <w:t xml:space="preserve"> </w:t>
  </w:r>
</w:p>
<w:p w:rsidR="003C2CC5" w:rsidRDefault="003C2CC5" w:rsidP="00FE63F7">
  <w:pPr>
    <w:pStyle w:val="berschrift3"/>
    <w:spacing w:before="240" w:after="60"/>
    <w:ind w:left="0" w:right="0"/>
  </w:pPr>
  <w:r>
    <w:rPr>
      <w:rFonts w:ascii="Arial" w:eastAsia="Arial" w:hAnsi="Arial" w:cs="Arial"/>
    </w:rPr>
    <w:t>3.{{ counter }}.4</w:t>
  </w:r>
  <w:r>
    <w:t xml:space="preserve"> </w:t>
  </w:r>
  <w:bookmarkStart w:id="26" w:name="_Toc164172955"/>
  <w:bookmarkEnd w:id="26"/>
  <w:r>
    <w:rPr>
      <w:rFonts w:ascii="Arial" w:eastAsia="Arial" w:hAnsi="Arial" w:cs="Arial"/>
    </w:rPr>
    <w:t>Vergleich mit bestehenden Lösungen</w:t>
  </w:r>
  <w:r>
    <w:t xml:space="preserve"> </w:t>
  </w:r>
</w:p>
<w:p w:rsidR="003C2CC5" w:rsidRDefault="003C2CC5" w:rsidP="00FE63F7">
  <w:pPr>
    <w:spacing w:after="220"/>
  </w:pPr>
  <w:r>
    <w:rPr>
      <w:rFonts w:ascii="Tahoma" w:eastAsia="Tahoma" w:hAnsi="Tahoma" w:cs="Tahoma"/>
      <w:sz w:val="20"/>
    </w:rPr>
    <w:t>&lt;Ihr Text&gt;</w:t>
  </w:r>
  <w:r>
    <w:t xml:space="preserve"> </w:t>
  </w:r>
</w:p>
<w:p w:rsidR="003C2CC5" w:rsidRDefault="003C2CC5" w:rsidP="00FE63F7">
  <w:pPr>
    <w:pStyle w:val="berschrift3"/>
    <w:spacing w:before="240" w:after="60"/>
    <w:ind w:left="0" w:right="0"/>
  </w:pPr>
  <w:r>
    <w:rPr>
      <w:rFonts w:ascii="Arial" w:eastAsia="Arial" w:hAnsi="Arial" w:cs="Arial"/>
    </w:rPr>
    <w:t>3.{{ counter }}.5</w:t>
  </w:r>
  <w:r>
    <w:t xml:space="preserve"> </w:t>
  </w:r>
  <w:bookmarkStart w:id="27" w:name="_Toc164172956"/>
  <w:bookmarkEnd w:id="27"/>
  <w:r>
    <w:rPr>
      <w:rFonts w:ascii="Arial" w:eastAsia="Arial" w:hAnsi="Arial" w:cs="Arial"/>
    </w:rPr>
    <w:t>Grobschätzung des Aufwands</w:t>
  </w:r>
  <w:r>
    <w:t xml:space="preserve"> </w:t>
  </w:r>
</w:p>
<w:p w:rsidR="003C2CC5" w:rsidRDefault="003C2CC5" w:rsidP="00FE63F7">
  <w:pPr>
    <w:spacing w:after="220"/>
  </w:pPr>
  <w:r>
    <w:rPr>
      <w:vanish />
    </w:rPr>
    <!-- set requirement id -->
    <w:t>{ "requirement-id": "{{ requirement.id }}", "requirement-state": "end" }</w:t>
    <!-- set requirement id -->
  </w:r>
  <w:r>
    <w:rPr>
      <w:rFonts w:ascii="Tahoma" w:eastAsia="Tahoma" w:hAnsi="Tahoma" w:cs="Tahoma"/>
      <w:sz w:val="20"/>
    </w:rPr>
    <w:t>&lt;Ihr Text&gt;</w:t>
  </w:r>
  <w:r>
    <w:t xml:space="preserve"> </w:t>
  </w:r>
</w:p>
